funEnsemble/__init__.py
funEnsemble/functional_ensemble_clustering.py
funEnsemble-0.1.0.dist-info/LICENSE
funEnsemble-0.1.0.dist-info/METADATA
funEnsemble-0.1.0.dist-info/WHEEL
funEnsemble-0.1.0.dist-info/top_level.txt
funEnsemble-0.1.0.dist-info/RECORD
