Metadata-Version: 2.1
Name: funEnsemble
Version: 0.1.0
Summary: Ensemble Clustering for Functional Data
Home-page: https://github.com/Newman251/funEnsemble
Author: Luke Newman
Author-email: newmanlu@tcd.ie
Classifier: Programming Language :: Python :: 3
Classifier: License :: OSI Approved :: MIT License
Classifier: Operating System :: OS Independent
Requires-Python: >=3.7
License-File: LICENSE
